mkdocs_strings_replacement/__init__.py
mkdocs_strings_replacement/config.py
mkdocs_strings_replacement/logger.py
mkdocs_strings_replacement/plugin.py
mkdocs_strings_replacement/py.typed
mkdocs_strings_replacement-0.1.0.dist-info/METADATA
mkdocs_strings_replacement-0.1.0.dist-info/WHEEL
mkdocs_strings_replacement-0.1.0.dist-info/entry_points.txt
mkdocs_strings_replacement-0.1.0.dist-info/licenses/LICENSE
mkdocs_strings_replacement-0.1.0.dist-info/RECORD
